{
  "task": "skill_cycle_optimizer",
  "timestamp": "2026-05-03T00:01:54.434627",
  "current_index": 160,
  "total_skills": 180,
  "current": {
    "skill": "node-inspect-debugger",
    "category": "software-development/node-inspect-debugger",
    "type": "sandbox",
    "metrics": {
      "latency_ms": 0,
      "success": true,
      "output_valid": true,
      "error": ""
    },
    "audit": {
      "doc_complete": "pass",
      "dep_available": "pass",
      "load_time_ms": 0,
      "error_rate_pct": 0.0,
      "perf_stable": "stable",
      "output_valid": true
    },
    "vs_last": {
      "delta_pct": 0.0
    },
    "suggestions": [],
    "status": "healthy"
  },
  "summary": {
    "audit_passed": 3,
    "audit_warnings": 0,
    "action": "OK"
  }
}